[{"id":"33883","available":false,"name":"Аппарат для безвоздушной покраски 650Вт 1.1л/мин 210бар Profi SIGMA (6816561)","price":16531.0,"vendor":"Sigma","vendorCode":"6816561","categoryId":1332,"pictures":["https://sigma.ua/upload/iblock/7c1/7c1c2d01dc76f6d71a85fc067b829525.jpg","https://sigma.ua/upload/iblock/277/2779ba14ed84620b928545c9afa0e04d.jpg","https://sigma.ua/upload/iblock/3cf/3cf22602c3dd24e66f66f8de991f2895.jpg","https://sigma.ua/upload/iblock/798/79813dbe53ac86e370c1f059613de50e.jpg","https://sigma.ua/upload/iblock/882/88216a8107eb6dbe2936d6c29041ed2d.jpg","https://sigma.ua/upload/iblock/e1d/e1dd243aa08e0e0cd4cec92210f020a9.jpg","https://sigma.ua/upload/iblock/fa2/o01xi6liqdek5qa947nc783r10itbrc2.jpg","https://sigma.ua/upload/iblock/fc0/fc010dbc0247c26f810573e7ddf01eab.jpg"],"description":"Гарантийный срок эксплуатации изделия - 12 месяца со дня продажи. При условии регистрации изделия в течение 1 месяца со дня продажи гарантия составит 12 месяцев >>> подробнее \n\n\n \n Подтверждением покупки является корректно заполненный гарантийный талон.\n\n\n \n Аппарат для безвоздушной покраски 650Вт 1.1л/мин 210бар Profi SIGMA (6816561) предназначен для окраски методом распыления краски под высоким давлением.\n\n\n \n Принцип действия аппарата основан на дроблении ЛКМ при нанесении его с большой скоростью через сопло пистолета-краскораспылителя на поверхность что окрашивается. Данный аппарат используют для получения идеально окрашенной поверхности с меньшими затратами времени и сил, чем этого требует покраска с помощью кистей или валиков.\n\n\n \n Аппарат применяется для нанесения ЛКМ на фасады домов, крыши, потолки, стены и тому подобное. Нанесение краски методом безвоздушной окраски, когда краска наносится на поверхность с помощью диспергирования лакокрасочных веществ, позволяет получить качественную пленку, которая не только придает поверхности презентабельный внешний вид, но и защищает ее от неблагоприятных воздействий внешней среды.\n\n\n \n Безвоздушная окраска дает возможность использовать ЛКМ, содержащие меньшее количество растворителей. Данная методика способствует уменьшению общего количества слоев благодаря увеличению толщины каждого слоя краски. Одним из ключевых преимуществ является отсутствие воздуха в струе ЛКМ, а также различных посторонних частиц. Это обеспечивается благодаря высокой скорости выброса струи ЛКМ из сопла.\n\n\n Характеристики: \n \n\n\n \n Высокая производительность \n \n Уменьшение количества слоев покраски \n \n Отсутствие туманообразования \n \n Сниженный расход покрасочных материалов \n \n Снижение загрязнения окружающей среды \n \n Рекомендуемая дистанция для нанесения ЛКМ - 300 мм \n \n Ширина факела - 250-310 мм \n \n Длина кабеля электропитания - 3 м \n \n Вес - 9.5 кг \n \n Габаритные размеры (длина) - 460×400×490 мм \n \n \n\n\n \n ВНИМАНИЕ!!! Категорически запрещается использовать абразивосодержащие ЛКМ","params":[{"name":"Артикул","value":"6816561"},{"name":"Мощность, Вт","value":"650"},{"name":"Напряжение","value":"U 1 ~ 230 ± 10% В"},{"name":"Максимально допустимое давление, бар","value":"210"},{"name":"Длина шланга, м","value":"7.5"},{"name":"Сила тока, А","value":"2.0-4.5"},{"name":"Официальная гарантия","value":"От производителя"},{"name":"Кратність","value":"1"}]},{"id":"34809","available":true,"name":"Аппарат для безвоздушной покраски компакт 650Вт 1.1л/мин 210бар Profi SIGMA (6816551)","price":13296.0,"vendor":"Sigma","vendorCode":"6816551","categoryId":1332,"pictures":["https://sigma.ua/upload/iblock/0b4/k78pq1e5bnnwpgwpkocc0f31n5tplld3.jpg","https://sigma.ua/upload/iblock/152/cwcf4ovcoypwn1y16enlzpwg1l8k47ge.jpg","https://sigma.ua/upload/iblock/1b4/2tnou2czzam97jbspoq91diimh2rspre.jpg","https://sigma.ua/upload/iblock/2e4/fq7x4dbnm6yum0nnmslbsyhv8vn7uf78.jpg","https://sigma.ua/upload/iblock/614/x5anwk1wsdbp2qy4tbau60a8utqesm7l.jpg","https://sigma.ua/upload/iblock/702/lye9rkhxqf1jsvg4l1xhm4wvqycidbzn.jpg","https://sigma.ua/upload/iblock/76f/axeh7lt1ye64ecy8chs34m5t44h182cn.jpg","https://sigma.ua/upload/iblock/a70/tiun2e645jwwifnur37bocbqh0ydtio9.jpg"],"description":"Гарантийный срок эксплуатации изделия - 12 месяца со дня продажи. При условии регистрации изделия в течение 1 месяца со дня продажи гарантия составит 12 месяцев >>> подробнее \n\n\n \n Подтверждением покупки является корректно заполненный гарантийный талон.\n\n\n \n Аппарат для безвоздушной покраски компакт 650Вт 1.1л/мин 210бар Profi SIGMA (6816551) предназначен для выполнения покраски распылением под высоким давлением и основан на дроблении ЛКМ при нанесении его с большой скоростью через сопло пистолета-краскораспылителя на окрашиваемую поверхность.\n\n\n \n Используют чтобы достичь идеального результата с меньшими затратами времени и сил, чем этого требует покраска с помощью кистей или валиков.\n\n\n \n Применяется для нанесения лакокрасочных материалов на стены домов, крыши, потолки, фасады.\n\n\n Особенности: \n \n\n\n \n Высокая производительность \n \n Уменьшение количества слоев окрашивания \n \n Отсутствие туманообразования \n \n Снижение расхода красящих материалов \n \n Снижение загрязнения окружающей среды \n \n \n\n\n Характеристики: \n \n\n\n \n Напряжение, В / Частота, Гц: 220/50 \n \n Тип двигателя: щеточный \n \n Мощность двигателя, Вт: 650 \n \n Максимальная производительность, л/мин: 1.1 \n \n Максимальное давление, бар: 210 \n \n Длина шланга, м: 7.5 \n \n Сопло: 517 \n \n Рекомендуемая дистанция для нанесения ЛКМ, мм: 300 \n \n Ширина факела распила, мм: 250-310 \n \n Удлинитель для пистолета, м: - \n \n Длина кабеля электропитания, м: 1.8 \n \n Вес, кг: 9.5 \n \n \n\n\n Комплектация: \n \n\n\n \n Аппарат высокого давления \n \n Шланг высокого давления \n \n Краскораспылитель \n \n Инструкция по эксплуатации \n \n Гарантийный талон \n \n Упаковка","params":[{"name":"Артикул","value":"6816551"},{"name":"Мощность, Вт","value":"650"},{"name":"Напряжение","value":"U 1 ~ 230 ± 10% В"},{"name":"Частота, Гц","value":"50"},{"name":"Длина кабеля, м","value":"1.8"},{"name":"Длина шланга, м","value":"7.5"},{"name":"Максимальное давление, бар","value":"210"},{"name":"Официальная гарантия","value":"От производителя"},{"name":"Вес брутто (единицы), кг","value":"9.5"},{"name":"Кратність","value":"1"}]},{"id":"34810","available":true,"name":"Аппарат для безвоздушной покраски 750Вт 2.1л/мин 210бар Profi SIGMA (6816601)","price":32648.0,"vendor":"Sigma","vendorCode":"6816601","categoryId":1332,"pictures":["https://sigma.ua/upload/iblock/7df/6ap1fgjguhlvrht8wyxq30b4hb8j4fhr.jpg","https://sigma.ua/upload/iblock/2c0/gy0xfljelzfuj1ox809xj3as7teb4lcp.jpg","https://sigma.ua/upload/iblock/309/1s3l6fggjgzqg0jmug87rimatj066xqd.jpg","https://sigma.ua/upload/iblock/9b7/6trnjob68zdemmp75spvg8pj0yuv67mr.jpg","https://sigma.ua/upload/iblock/9c7/0gj4zv8jbi9usp9x0zdn4tc7s5vofeye.jpg","https://sigma.ua/upload/iblock/a2c/2i1anmplsnabm90ngrz5kt6d3216w6xh.jpg","https://sigma.ua/upload/iblock/d76/mg400f2wogw02jgvlrihv6s1bof77sgd.jpg","https://sigma.ua/upload/iblock/f7a/z51ypiwxe7q4zd1svlxbfjq4qeyt26s9.jpg"],"description":"Аппарат для безвоздушной покраски 750Вт 2.1л/мин 210бар Profi SIGMA (6816601) предназначен для выполнения покраски распылением под высоким давлением и основан на дроблении ЛКМ при нанесении его с большой скоростью через сопло пистолета-краскораспылителя на окрашиваемую поверхность.\n\n\n \n Используют чтобы достичь идеального результата с меньшими затратами времени и сил, чем этого требует покраска с помощью кистей или валиков.\n\n\n \n Применяется для нанесения лакокрасочных материалов на стены домов, крыши, потолки, фасады.","params":[{"name":"Артикул","value":"6816601"},{"name":"Мощность, Вт","value":"750"},{"name":"Напряжение","value":"U 1 ~ 230 ± 10% В"},{"name":"Частота, Гц","value":"50"},{"name":"Длина кабеля, м","value":"1.8"},{"name":"Длина шланга, м","value":"15"},{"name":"Максимальное давление, бар","value":"210"},{"name":"Официальная гарантия","value":"От производителя"},{"name":"Масса, кг","value":"18"},{"name":"Кратність","value":"1"}]},{"id":"34811","available":true,"name":"Аппарат для безвоздушной покраски 2200Вт 3.2л/мин 225бар Profi SIGMA (6816631)","price":51823.0,"vendor":"Sigma","vendorCode":"6816631","categoryId":1332,"pictures":["https://sigma.ua/upload/iblock/9c3/vttcth2ez30ufw6suem7mhhcamimarc6.jpg","https://sigma.ua/upload/iblock/032/91domf28fqa28ytahftq454ktjl2fase.jpg","https://sigma.ua/upload/iblock/2dd/ltc6i8ytcc4nweu0wz9rlhts2jtr1rwx.jpg","https://sigma.ua/upload/iblock/426/wq2f642plm5wu8ghng0ucawud12fh5f1.jpg","https://sigma.ua/upload/iblock/58a/r81yk6l2842nu6h8h6zt61myn9qxwibt.jpg","https://sigma.ua/upload/iblock/906/rvn0wwux9hv8wiynp2hhu2shons7ijy4.jpg","https://sigma.ua/upload/iblock/912/7gl4n333bfo075tsieimjllkfqtfig7t.jpg","https://sigma.ua/upload/iblock/9f8/21ttm31h1wo02hfi8dkj91dromk7j98y.jpg"],"description":"Аппарат для безвоздушной покраски 2200Вт 3.2л/мин 225бар Profi SIGMA (6816631) предназначен для выполнения покраски распылением под высоким давлением и основан на дроблении ЛКМ при нанесении его с большой скоростью через сопло пистолета-краскораспылителя на окрашиваемую поверхность.\n\n\n \n Используют чтобы достичь идеального результата с меньшими затратами времени и сил, чем этого требует покраска с помощью кистей или валиков.\n\n\n \n Применяется для нанесения лакокрасочных материалов на стены домов, крыши, потолки, фасады.","params":[{"name":"Артикул","value":"6816631"},{"name":"Мощность, Вт","value":"2200"},{"name":"Напряжение","value":"U 1 ~ 230 ± 10% В"},{"name":"Частота, Гц","value":"50"},{"name":"Длина кабеля, м","value":"1.8"},{"name":"Длина шланга, м","value":"15"},{"name":"Максимальное давление, бар","value":"225"},{"name":"Официальная гарантия","value":"От производителя"},{"name":"Масса, кг","value":"22"},{"name":"Кратність","value":"1"}]},{"id":"34812","available":true,"name":"Аппарат для безвоздушной покраски и шпатлевки 3800Вт 6.0л/мин 250бар Profi SIGMA (6816671)","price":143327.0,"vendor":"Sigma","vendorCode":"6816671","categoryId":1332,"pictures":["https://sigma.ua/upload/iblock/cd7/l280ss9qaq8k96jk9ctldkom65ttm3hc.jpg","https://sigma.ua/upload/iblock/293/mg0f4trqp1m8r1xozxb1aqjio0m0hd5t.jpg","https://sigma.ua/upload/iblock/5e7/gfpr1dmv429jbb7co0ntuobdot411czj.jpg","https://sigma.ua/upload/iblock/825/bq3p7oeaa1ob626dbanlnmq81xj21vj8.jpg","https://sigma.ua/upload/iblock/996/px3x0h44h8kasu4le31yrtujp8kvcakd.jpg","https://sigma.ua/upload/iblock/c53/xcuis0e4kcz6psq0cqhou2mss4cb6h66.jpg","https://sigma.ua/upload/iblock/d11/4lab991zw1w5ef61wkzyp507zi10jr6p.jpg","https://sigma.ua/upload/iblock/f72/kek2a1dne6tmu9jp79kzxjixrt0uq4ns.jpg"],"description":"Аппарат для безвоздушной покраски и шпатлевки 3800Вт 6.0л/мин 250бар Profi SIGMA (6816671) предназначен для выполнения покраски распылением под высоким давлением и основан на дроблении ЛКМ при нанесении его с большой скоростью через сопло пистолета-краскораспылителя на окрашиваемую поверхность.\n\n\n \n Используют чтобы достичь идеального результата с меньшими затратами времени и сил, чем этого требует покраска с помощью кистей или валиков.\n\n\n \n Применяется для нанесения лакокрасочных материалов на стены домов, крыши, потолки, фасады.","params":[{"name":"Артикул","value":"6816671"},{"name":"Мощность, Вт","value":"3800"},{"name":"Напряжение","value":"U 1 ~ 230 ± 10% В"},{"name":"Частота, Гц","value":"50"},{"name":"Длина кабеля, м","value":"1.8"},{"name":"Длина шланга, м","value":"30"},{"name":"Максимальное давление, бар","value":"250"},{"name":"Официальная гарантия","value":"От производителя"},{"name":"Масса, кг","value":"55"},{"name":"Кратність","value":"1"}]},{"id":"34814","available":true,"name":"Держатель сопла краскораспылителя для аппарата безвоздушной покраски SIGMA (6818071)","price":470.0,"vendor":"Sigma","vendorCode":"6818071","categoryId":1332,"pictures":["https://sigma.ua/upload/iblock/f61/vyvpcf5uue52yyfp98t96xdeso4409j8.jpg","https://sigma.ua/upload/iblock/829/alou1l1avicci4l7mpwxdv82ms46jjio.jpg","https://sigma.ua/upload/iblock/fb4/6dajn2liw3wgwnky4oogi0kh1yk7m21u.jpg"],"description":"Держатель сопла краскораспылителя для аппарата безвоздушной покраски SIGMA (6818071)","params":[{"name":"Артикул","value":"6818071"},{"name":"Официальная гарантия","value":"От производителя"},{"name":"Кратність","value":"1"}]},{"id":"34815","available":true,"name":"Удлинитель краскораспылителя для аппарата безвоздушной покраски 0.6м SIGMA (6818141)","price":444.0,"vendor":"Sigma","vendorCode":"6818141","categoryId":1332,"pictures":["https://sigma.ua/upload/iblock/2c6/1uwg3otp5ope5rnifb5iwzeg0jpkgpt5.jpg","https://sigma.ua/upload/iblock/25f/044gn7d8cavzlqr824e6r7qqwew7rztk.jpg","https://sigma.ua/upload/iblock/441/teydjopcn5lkcd4q89ad0yuuzeackb23.jpg","https://sigma.ua/upload/iblock/d44/lscphk309aka44sr6poz0apbnvn60sa0.jpg"],"description":"Удлинитель краскораспылителя для аппарата безвоздушной покраски 0.6м SIGMA (6818141)","params":[{"name":"Артикул","value":"6818141"},{"name":"Длина, м","value":"0.6"},{"name":"Официальная гарантия","value":"От производителя"},{"name":"Кратність","value":"1"}]},{"id":"34816","available":true,"name":"Удлинитель краскораспылителя для аппарата безвоздушной покраски 1.0м SIGMA (6818151)","price":513.0,"vendor":"Sigma","vendorCode":"6818151","categoryId":1332,"pictures":["https://sigma.ua/upload/iblock/36e/ansv19bva1aw9bieg7x2141nbxfweh4k.jpg","https://sigma.ua/upload/iblock/30d/jj5y3zz0pw9vnka4r6iv3acky3w3a7bc.jpg","https://sigma.ua/upload/iblock/6bb/gs70vt5fqr65rltj9l8ajg92r9c45dem.jpg","https://sigma.ua/upload/iblock/e54/823hekplctu7ujirq50guqno6c72o35a.jpg"],"description":"Удлинитель краскораспылителя для аппарата безвоздушной покраски 1.0м SIGMA (6818151)","params":[{"name":"Артикул","value":"6818151"},{"name":"Длина, м","value":"1"},{"name":"Официальная гарантия","value":"От производителя"},{"name":"Кратність","value":"1"}]},{"id":"34817","available":true,"name":"Шланг для аппарата безвоздушной покраски 7.6м SIGMA (6818221)","price":1644.0,"vendor":"Sigma","vendorCode":"6818221","categoryId":1332,"pictures":["https://sigma.ua/upload/iblock/3eb/8qhchk5dcs8wk5gu76k9o9jbdzl705ff.jpg","https://sigma.ua/upload/iblock/718/etrrz5e34213p5q2qs3t6uffb5f6kvf8.jpg","https://sigma.ua/upload/iblock/c4a/i31otr9783zyt7bcsy9nm171ek11xdw8.jpg"],"description":"Шланг для аппарата безвоздушной покраски 7.6м SIGMA (6818221)","params":[{"name":"Артикул","value":"6818221"},{"name":"Длина шланга, м","value":"7.6"},{"name":"Официальная гарантия","value":"От производителя"},{"name":"Кратність","value":"1"}]},{"id":"34818","available":false,"name":"Шланг для аппарата безвоздушной покраски 15м SIGMA (6818231)","price":3235.0,"vendor":"Sigma","vendorCode":"6818231","categoryId":1332,"pictures":["https://sigma.ua/upload/iblock/44d/jgu8lfp5dlgyynbl5sqnyw93fo2rxjot.jpg","https://sigma.ua/upload/iblock/066/2wbfb7togeplw1yjiewhvscbqfhzn9eb.jpg","https://sigma.ua/upload/iblock/f35/dp594ql1v8ygydst8tm6219lnlgq9gkm.jpg"],"description":"Шланг для аппарата безвоздушной покраски 15м SIGMA (6818231)","params":[{"name":"Артикул","value":"6818231"},{"name":"Длина шланга, м","value":"15"},{"name":"Официальная гарантия","value":"От производителя"},{"name":"Кратність","value":"1"}]},{"id":"34819","available":true,"name":"Фильтр для краскораспылителей аппарата безвоздушной покраски сетка 0.25мм SIGMA (6818311)","price":143.0,"vendor":"Sigma","vendorCode":"6818311","categoryId":1332,"pictures":["https://sigma.ua/upload/iblock/2c4/290yxie6ch8bhrdbln9yg8b3z8r3z0yr.jpg"],"description":"Фильтр для краскораспылителей аппарата безвоздушной покраски сетка 0.25мм SIGMA (6818311)","params":[{"name":"Артикул","value":"6818311"},{"name":"Официальная гарантия","value":"От производителя"},{"name":"Кратність","value":"1"}]},{"id":"34820","available":true,"name":"Фильтр для краскораспылителей аппарата безвоздушной покраски сетка 0.149мм SIGMA (6818321)","price":143.0,"vendor":"Sigma","vendorCode":"6818321","categoryId":1332,"pictures":["https://sigma.ua/upload/iblock/7c0/g4o2f5bv35rgvfsdwvv82ray0uhj84kc.jpg"],"description":"Фильтр для краскораспылителей аппарата безвоздушной покраски сетка 0.149мм SIGMA (6818321)","params":[{"name":"Артикул","value":"6818321"},{"name":"Кратність","value":"1"}]},{"id":"34821","available":true,"name":"Фильтр для краскораспылителей аппарата безвоздушной покраски сетка 0.098мм SIGMA (6818331)","price":143.0,"vendor":"Sigma","vendorCode":"6818331","categoryId":1332,"pictures":["https://sigma.ua/upload/iblock/38c/115ufhue6hguk8zr6co3d0951vib4o0o.jpg"],"description":"Фильтр для краскораспылителей аппарата безвоздушной покраски сетка 0.098мм SIGMA (6818331)","params":[{"name":"Артикул","value":"6818331"},{"name":"Официальная гарантия","value":"От производителя"},{"name":"Кратність","value":"1"}]},{"id":"34822","available":true,"name":"Фильтр для аппарата безвоздушной покраски сетка 0.25мм для 6816601, 6816631 SIGMA (6818361)","price":202.0,"vendor":"Sigma","vendorCode":"6818361","categoryId":1332,"pictures":["https://sigma.ua/upload/iblock/4a1/kzjux6565ahmf50s7h0zgxtzxef4safm.jpg","https://sigma.ua/upload/iblock/a52/qlsux0xwfywcgdglifin58dtfuzgzs6a.jpg","https://sigma.ua/upload/iblock/b5a/7i9mbhh1z5ch29p188189lulipr19phr.jpg"],"description":"Фильтр для аппарата безвоздушной покраски сетка 0.25мм SIGMA (6818361) \n\n\n \n\n\n \n для 6816601 , 6816631","params":[{"name":"Артикул","value":"6818361"},{"name":"Официальная гарантия","value":"От производителя"},{"name":"Кратність","value":"1"}]},{"id":"34823","available":true,"name":"Фильтр для аппарата безвоздушной покраски сетка 0.177мм для 6816671 SIGMA (6818371)","price":310.0,"vendor":"Sigma","vendorCode":"6818371","categoryId":1332,"pictures":["https://sigma.ua/upload/iblock/bfa/9j1w66orby41apqelr4n2bfq50w68cj8.jpg","https://sigma.ua/upload/iblock/43e/3icoksck76ljs10npwozj2bccc1ylpdy.jpg","https://sigma.ua/upload/iblock/4de/wjgpiqwob1ywrdw91saqgllqipzxve9u.jpg"],"description":"Фильтр для аппарата безвоздушной покраски сетка 0.177мм SIGMA (6818371) \n\n\n \n\n\n \n для 6816671","params":[{"name":"Артикул","value":"6818371"},{"name":"Официальная гарантия","value":"От производителя"},{"name":"Кратність","value":"1"}]},{"id":"34824","available":true,"name":"Сопло 313 для краскораспылителя аппарата безвоздушной покраски (сопло 0.013\"/0.33мм, факел 30°) SIGMA (6819171)","price":512.0,"vendor":"Sigma","vendorCode":"6819171","categoryId":1332,"pictures":["https://sigma.ua/upload/iblock/a53/hpcu4eoghswqroscz0zday9a9y2rsegq.jpg"],"description":"Сопло 313 для краскораспылителя аппарата безвоздушной покраски (сопло 0.013\"/0.33мм, факел 30°) SIGMA (6819171)","params":[{"name":"Артикул","value":"6819171"},{"name":"Официальная гарантия","value":"От производителя"},{"name":"Особенности","value":"сопло 0.013&quot;/0.33мм, факел 30°"},{"name":"Кратність","value":"1"}]},{"id":"34825","available":true,"name":"Сопло 413 для краскораспылителя аппарата безвоздушной покраски (сопло 0.013\"/0.33мм, факел 40°) SIGMA (6819181)","price":512.0,"vendor":"Sigma","vendorCode":"6819181","categoryId":1332,"pictures":["https://sigma.ua/upload/iblock/299/10wh3jy5c3d7s3voakprx6z41ueoca3s.jpg"],"description":"Сопло 413 для краскораспылителя аппарата безвоздушной покраски (сопло 0.013\"/0.33мм, факел 40°) SIGMA (6819181)","params":[{"name":"Артикул","value":"6819181"},{"name":"Официальная гарантия","value":"От производителя"},{"name":"Особенности","value":"сопло 0.013&quot;/0.33мм, факел 40°"},{"name":"Кратність","value":"1"}]},{"id":"34826","available":true,"name":"Сопло 513 для краскораспылителя аппарата безвоздушной покраски (сопло 0.013\"/0.33мм, факел 50°) SIGMA (6819191)","price":512.0,"vendor":"Sigma","vendorCode":"6819191","categoryId":1332,"pictures":["https://sigma.ua/upload/iblock/898/iotmiy2yo5c4sg82vlu062scibiaz0ob.jpg"],"description":"Сопло 513 для краскораспылителя аппарата безвоздушной покраски (сопло 0.013\"/0.33мм, факел 50°) SIGMA (6819191)","params":[{"name":"Артикул","value":"6819191"},{"name":"Официальная гарантия","value":"От производителя"},{"name":"Особенности","value":"сопло 0.013&quot;/0.33мм, факел 50°"},{"name":"Кратність","value":"1"}]},{"id":"34827","available":true,"name":"Сопло 315 для краскораспылителя аппарата безвоздушной покраски (сопло 0.015\"/0.38мм, факел 30°) SIGMA (6819231)","price":512.0,"vendor":"Sigma","vendorCode":"6819231","categoryId":1332,"pictures":["https://sigma.ua/upload/iblock/989/xb7wuobj4qhpoutscv52eie6wq689n2e.jpg"],"description":"Сопло 315 для краскораспылителя аппарата безвоздушной покраски (сопло 0.015\"/0.38мм, факел 30°) SIGMA (6819231)","params":[{"name":"Артикул","value":"6819231"},{"name":"Официальная гарантия","value":"От производителя"},{"name":"Особенности","value":"сопло 0.015&quot;/0.38мм, факел 30°"},{"name":"Кратність","value":"1"}]},{"id":"34828","available":true,"name":"Сопло 415 для краскораспылителя аппарата безвоздушной покраски (сопло 0.015\"/0.38мм, факел 40°) SIGMA (6819241)","price":512.0,"vendor":"Sigma","vendorCode":"6819241","categoryId":1332,"pictures":["https://sigma.ua/upload/iblock/b1d/2b0w5jr0jl1wtsuoxtue3qtusa98ofi9.jpg"],"description":"Сопло 415 для краскораспылителя аппарата безвоздушной покраски (сопло 0.015\"/0.38мм, факел 40°) SIGMA (6819241)","params":[{"name":"Артикул","value":"6819241"},{"name":"Официальная гарантия","value":"От производителя"},{"name":"Особенности","value":"сопло 0.015&quot;/0.38мм, факел 40°"},{"name":"Кратність","value":"1"}]},{"id":"34829","available":false,"name":"Сопло 515 для краскораспылителя аппарата безвоздушной покраски (сопло 0.015\"/0.38мм, факел 50°) SIGMA (6819251)","price":512.0,"vendor":"Sigma","vendorCode":"6819251","categoryId":1332,"pictures":["https://sigma.ua/upload/iblock/73c/qx0b7w5uit472hq7wepz8xdq7mwahsp9.jpg"],"description":"Сопло 515 для краскораспылителя аппарата безвоздушной покраски (сопло 0.015\"/0.38мм, факел 50°) SIGMA (6819251)","params":[{"name":"Артикул","value":"6819251"},{"name":"Официальная гарантия","value":"От производителя"},{"name":"Особенности","value":"сопло 0.015&quot;/0.38мм, факел 50°"},{"name":"Кратність","value":"1"}]},{"id":"34830","available":true,"name":"Сопло 517 для краскораспылителя аппарата безвоздушной покраски (сопло 0.017\"/0.43мм, факел 50°) SIGMA (6819311)","price":512.0,"vendor":"Sigma","vendorCode":"6819311","categoryId":1332,"pictures":["https://sigma.ua/upload/iblock/077/85bwffm3bya0n16liadgpyjbv5159v0l.jpg"],"description":"Сопло 517 для краскораспылителя аппарата безвоздушной покраски (сопло 0.017\"/0.43мм, факел 50°) SIGMA (6819311)","params":[{"name":"Артикул","value":"6819311"},{"name":"Официальная гарантия","value":"От производителя"},{"name":"Особенности","value":"сопло 0.017&quot;/0.43мм, факел 50°"},{"name":"Кратність","value":"1"}]},{"id":"34831","available":true,"name":"Сопло 519 для краскораспылителя аппарата безвоздушной покраски (сопло 0.019\"/0.48мм, факел 50°) SIGMA (6819391)","price":512.0,"vendor":"Sigma","vendorCode":"6819391","categoryId":1332,"pictures":["https://sigma.ua/upload/iblock/307/lc48e39ea1ym5do4lippi74shl5jrhve.jpg"],"description":"Сопло 519 для краскораспылителя аппарата безвоздушной покраски (сопло 0.019\"/0.48мм, факел 50°) SIGMA (6819391)","params":[{"name":"Артикул","value":"6819391"},{"name":"Официальная гарантия","value":"От производителя"},{"name":"Особенности","value":"сопло 0.019&quot;/0.48мм, факел 50°"},{"name":"Кратність","value":"1"}]},{"id":"34832","available":true,"name":"Сопло 619 для краскораспылителя аппарата безвоздушной покраски (сопло 0.019\"/0.48мм, факел 60°) SIGMA (6819401)","price":512.0,"vendor":"Sigma","vendorCode":"6819401","categoryId":1332,"pictures":["https://sigma.ua/upload/iblock/0af/lxpzy8yaub9n7v43o19ez2krq2bp2uk4.jpg"],"description":"Сопло 619 для краскораспылителя аппарата безвоздушной покраски (сопло 0.019\"/0.48мм, факел 60°) SIGMA (6819401)","params":[{"name":"Артикул","value":"6819401"},{"name":"Официальная гарантия","value":"От производителя"},{"name":"Особенности","value":"сопло 0.019&quot;/0.48мм, факел 60°"},{"name":"Кратність","value":"1"}]},{"id":"34833","available":true,"name":"Сопло 521 для краскораспылителя аппарата безвоздушной покраски (сопло 0.021\"/0.53мм, факел 50°) SIGMA (6819461)","price":512.0,"vendor":"Sigma","vendorCode":"6819461","categoryId":1332,"pictures":["https://sigma.ua/upload/iblock/2f1/ykacbk74i86wzzbng1r9o7xpf43owifa.jpg"],"description":"Сопло 521 для краскораспылителя аппарата безвоздушной покраски (сопло 0.021\"/0.53мм, факел 50°) SIGMA (6819461)","params":[{"name":"Артикул","value":"6819461"},{"name":"Официальная гарантия","value":"От производителя"},{"name":"Особенности","value":"сопло 0.021&quot;/0.53мм, факел 50°"},{"name":"Кратність","value":"1"}]},{"id":"34834","available":true,"name":"Сопло 621 для краскораспылителя аппарата безвоздушной покраски (сопло 0.021\"/0.53мм, факел 60°) SIGMA (6819471)","price":512.0,"vendor":"Sigma","vendorCode":"6819471","categoryId":1332,"pictures":["https://sigma.ua/upload/iblock/2fb/8imixrpgzo9jkgsj3vmh16pmbflw6sg7.jpg"],"description":"Сопло 621 для краскораспылителя аппарата безвоздушной покраски (сопло 0.021\"/0.53мм, факел 60°) SIGMA (6819471)","params":[{"name":"Артикул","value":"6819471"},{"name":"Официальная гарантия","value":"От производителя"},{"name":"Особенности","value":"сопло 0.021&quot;/0.53мм, факел 60°"},{"name":"Кратність","value":"1"}]}]